setup.py
digSparkUtil/ESUtil.py
digSparkUtil/__init__.py
digSparkUtil/convertToSeq.py
digSparkUtil/dictUtil.py
digSparkUtil/fileUtil.py
digSparkUtil/hbase_manager.py
digSparkUtil/javaToPythonSpark.py
digSparkUtil/jsonUtil.py
digSparkUtil/listUtil.py
digSparkUtil/logUtil.py
digSparkUtil/miscUtil.py
digSparkUtil/rddUtil.py
digSparkUtil/seq2tsv.py
digSparkUtil/testESUtil.py
digSparkUtil.egg-info/PKG-INFO
digSparkUtil.egg-info/SOURCES.txt
digSparkUtil.egg-info/dependency_links.txt
digSparkUtil.egg-info/top_level.txt