Metadata-Version: 1.1
Name: digSparkUtil
Version: 1.0.22
Summary: digSparkUtil
Home-page: https://github.com/usc-isi-i2/dig-sparkutil
Author: Andrew Philpot
Author-email: andrew.philpot@gmail.com
License: UNKNOWN
Download-URL: https://github.com/usc-isi-i2/dig-sparkutil
Platform: UNKNOWN
